commandlet/__init__.py
commandlet/commands.py
commandlet/exc.py
commandlet/filters.py
commandlet/parser.py
commandlet-0.4.4.dist-info/AUTHORS
commandlet-0.4.4.dist-info/LICENSE
commandlet-0.4.4.dist-info/METADATA
commandlet-0.4.4.dist-info/WHEEL
commandlet-0.4.4.dist-info/pbr.json
commandlet-0.4.4.dist-info/top_level.txt
commandlet-0.4.4.dist-info/RECORD
