Metadata-Version: 2.1
Name: commandlet
Version: 0.4.4
Summary: Werkzeug-style command parsing.
Home-page: https://github.com/chrisnorman7/
Author: Chris Norman
Author-email: chris.norman2@googlemail.com
License: MPL-2
Platform: UNKNOWN
Requires-Dist: attrs
